racovimge/colors.txt
racovimge/racovimge.py
racovimge/__init__.py
racovimge/fonts/Unique.ttf
racovimge/fonts/Liberation Serif.ttf
racovimge/fonts/Great Vibes.otf
racovimge/fonts/Libre Baskerville.ttf
racovimge/fonts/Bradley Gratis.ttf
racovimge/fonts/Gidole.ttf
racovimge/fonts/Orkney.ttf
racovimge/fonts/Crimson.otf
racovimge/fonts/Caladea.ttf
racovimge/fonts/Sofia.otf
racovimge/fonts/Glacial Indifference.otf
racovimge/fonts/Horta.ttf
racovimge/fonts/Petit Formal Script.ttf
racovimge/fonts/Alex Brush.otf
racovimge/fonts/Bellota.otf
racovimge/templates/Simple.svg
racovimge/templates/Ornate Border 2.svg
racovimge/templates/Rings.svg
racovimge/templates/Ornate Corners 2.svg
racovimge/templates/Ornate Title 1.svg
racovimge/templates/Column.svg
racovimge/templates/Cross.svg
racovimge/templates/Gradient.svg
racovimge/templates/Ornate Border 1 Dark.svg
racovimge/templates/Ornate Title 1 Dark.svg
racovimge/templates/Ornate Border 1.svg
racovimge/templates/Simple Dark.svg
racovimge/templates/Ornate Border 2 Dark.svg
racovimge/templates/Ornate Corners 4.svg
racovimge/templates/Tiles.svg
racovimge/templates/Ornate Corners 3.svg
racovimge/templates/Window.svg
racovimge/templates/Ornate Corners 1.svg
racovimge/templates/Blocks.svg
racovimge-0.9.dist-info/WHEEL
racovimge-0.9.dist-info/RECORD
racovimge-0.9.dist-info/METADATA
racovimge-0.9.dist-info/metadata.json
racovimge-0.9.dist-info/DESCRIPTION.rst
racovimge-0.9.dist-info/top_level.txt
racovimge-0.9.data/scripts/racovimge
