Metadata-Version: 2.0
Name: racovimge
Version: 0.9
Summary: Random Cover Image Generator
Home-page: https://github.com/anqxyr/racovimge/
Author: anqxyr
Author-email: anqxyr@gmail.com
License: MIT
Platform: UNKNOWN
Classifier: Development Status :: 4 - Beta
Classifier: Intended Audience :: Developers
Classifier: Intended Audience :: Other Audience
Classifier: License :: OSI Approved :: MIT License
Classifier: Operating System :: POSIX :: Linux
Classifier: Programming Language :: Python :: 3.4
Classifier: Programming Language :: Python :: 3.5
Classifier: Programming Language :: Python :: 3.6
Classifier: Programming Language :: Python
Classifier: Topic :: Multimedia
Classifier: Topic :: Utilities
Requires-Dist: jinja2
